chaos_stratus/__init__.py
chaos_stratus/__main__.py
chaos_stratus/stratus.py
chaos_stratus-1.1.1.dist-info/METADATA
chaos_stratus-1.1.1.dist-info/WHEEL
chaos_stratus-1.1.1.dist-info/top_level.txt
chaos_stratus-1.1.1.dist-info/RECORD
