Metadata-Version: 2.1
Name: chaos-stratus
Version: 1.1.1
Summary: Python tools used to interact with Chaos Stratus effect libraries
Author-email: Martin Bartlett <martin.j.bartlett@gmail.com>
License: MIT License
Project-URL: Homepage, https://github.com/bassmanitram/chaos-stratus-python
Classifier: Programming Language :: Python
Classifier: Programming Language :: Python :: 3
Requires-Python: >=3.5
